{
  "total_records": 7,
  "document_types": {
    "evento_can": 5,
    "documentacion_tecnica": 2
  },
  "text_length_stats": {
    "mean": 663.5714285714286,
    "std": 108.24179282645736,
    "min": "488",
    "max": "858"
  },
  "redes_can": {
    "CAN_CUSTOM_31": 5,
    "DOCUMENTACION": 2
  },
  "eventos_vehiculo": {
    "carga": 5,
    "referencia_tecnica": 2
  },
  "cleaning_impact": {
    "avg_reduction_chars": 9.714285714285714,
    "cleaning_ratio": 0.9850202269163244
  },
  "quality_filtering": {
    "records_before": 7,
    "records_after": 7,
    "filtered_out": 0,
    "retention_rate": 1.0
  }
}